crashtest/__init__.py
crashtest/contracts/__init__.py
crashtest/contracts/base_solution.py
crashtest/contracts/has_solutions_for_exception.py
crashtest/contracts/provides_solution.py
crashtest/contracts/solution.py
crashtest/contracts/solution_provider_repository.py
crashtest/frame.py
crashtest/frame_collection.py
crashtest/inspector.py
crashtest/py.typed
crashtest/solution_providers/__init__.py
crashtest/solution_providers/solution_provider_repository.py
crashtest-0.4.0.dist-info/LICENSE
crashtest-0.4.0.dist-info/WHEEL
crashtest-0.4.0.dist-info/METADATA
crashtest-0.4.0.dist-info/RECORD
