Metadata-Version: 2.1
Name: crashtest
Version: 0.4.0
Summary: Manage Python errors with ease
Home-page: https://github.com/sdispater/crashtest
License: MIT
Author: Sébastien Eustace
Author-email: sebastien@eustace.io
Requires-Python: >=3.7,<4.0
Classifier: License :: OSI Approved :: MIT License
Classifier: Programming Language :: Python :: 3
Classifier: Programming Language :: Python :: 3.7
Classifier: Programming Language :: Python :: 3.8
Classifier: Programming Language :: Python :: 3.9
Classifier: Programming Language :: Python :: 3.10
Project-URL: Repository, https://github.com/sdispater/crashtest
